mkdocstrings_handlers/python_xref/VERSION
mkdocstrings_handlers/python_xref/__init__.py
mkdocstrings_handlers/python_xref/crossref.py
mkdocstrings_handlers/python_xref/handler.py
mkdocstrings_handlers/python_xref/py.typed
mkdocstrings_python_xref-1.16.4.dist-info/METADATA
mkdocstrings_python_xref-1.16.4.dist-info/WHEEL
mkdocstrings_python_xref-1.16.4.dist-info/licenses/LICENSE.md
mkdocstrings_python_xref-1.16.4.dist-info/RECORD
