Metadata-Version: 2.4
Name: mkdocstrings-python-xref
Version: 1.16.4
Summary: Enhanced mkdocstrings python handler
Project-URL: Repository, https://github.com/analog-garage/mkdocstrings-python-xref
Project-URL: Documentation, https://analog-garage.github.io/mkdocstrings-python-xref/
Author-email: Christopher Barber <Christopher.Barber@analog.com>
License-File: LICENSE.md
Keywords: documentation-tool,mkdocstrings,mkdocstrings-handler,python
Classifier: Development Status :: 5 - Production/Stable
Classifier: Intended Audience :: Developers
Classifier: Programming Language :: Python :: 3.9
Classifier: Programming Language :: Python :: 3.10
Classifier: Programming Language :: Python :: 3.11
Classifier: Programming Language :: Python :: 3.12
Classifier: Programming Language :: Python :: 3.13
Classifier: Topic :: Software Development :: Documentation
Requires-Python: >=3.9
Requires-Dist: griffe>=1.0
Requires-Dist: mkdocstrings-python<2.0,>=1.16.6
Provides-Extra: dev
Requires-Dist: beautifulsoup4>=4.12; extra == 'dev'
Requires-Dist: black>=23.12; extra == 'dev'
Requires-Dist: build>=1.0.0; extra == 'dev'
Requires-Dist: coverage>=7.4.0; extra == 'dev'
Requires-Dist: hatchling>=1.21; extra == 'dev'
Requires-Dist: linkchecker>=10.4; extra == 'dev'
Requires-Dist: mike>=1.1; extra == 'dev'
Requires-Dist: mkdocs-material>=9.5.4; extra == 'dev'
Requires-Dist: mkdocs<2.0,>=1.5.3; extra == 'dev'
Requires-Dist: mypy>=1.10; extra == 'dev'
Requires-Dist: pytest-cov>=5.0; extra == 'dev'
Requires-Dist: pytest>=8.2; extra == 'dev'
Requires-Dist: ruff>=0.4.10; extra == 'dev'
